proteingraph/__init__.py
proteingraph/conversion.py
proteingraph/features.py
proteingraph/pin.py
proteingraph/resi_atoms.py
proteingraph/test_conversion.py
proteingraph/test_pin.py
proteingraph-0.3.0.dist-info/LICENSE
proteingraph-0.3.0.dist-info/METADATA
proteingraph-0.3.0.dist-info/WHEEL
proteingraph-0.3.0.dist-info/top_level.txt
proteingraph-0.3.0.dist-info/RECORD
