Metadata-Version: 2.1
Name: proteingraph
Version: 0.3.0
Summary: A package for making graph representations of proteinstructures.
Home-page: http://github.com/ericmjl/protein-interaction-network/
Author: Eric J. Ma
Author-email: ericmajinglong@gmail.com
License: MIT
Keywords: protein,biochemistry,structural biology,graph theory
Platform: UNKNOWN
Classifier: Development Status :: 3 - Alpha
Classifier: Intended Audience :: Science/Research
Classifier: Topic :: Scientific/Engineering :: Bio-Informatics
Classifier: Topic :: Scientific/Engineering :: Mathematics
Classifier: License :: OSI Approved :: MIT License
Classifier: Programming Language :: Python :: 3
